fibretracker/__init__.py
fibretracker/io/__init__.py
fibretracker/io/read_file.py
fibretracker/models/__init__.py
fibretracker/models/detector.py
fibretracker/models/tracker.py
fibretracker/viz/__init__.py
fibretracker/viz/plotting.py
fibretracker/viz/visualize.py
fibretracker-0.1.0.dist-info/LICENSE
fibretracker-0.1.0.dist-info/METADATA
fibretracker-0.1.0.dist-info/WHEEL
fibretracker-0.1.0.dist-info/top_level.txt
fibretracker-0.1.0.dist-info/RECORD
